{
  "project_info": {
    "project_number": "325462268268",
    "project_id": "proiectandroiddami",
    "storage_bucket": "proiectandroiddami.appspot.com"
  },
  "client": [
    {
      "client_info": {
        "mobilesdk_app_id": "1:325462268268:android:6cc4cb18bcf0a7aabb7b49",
        "android_client_info": {
          "package_name": "com.example.proiectandroiddami"
        }
      },
      "oauth_client": [
        {
          "client_id": "325462268268-2q8v22r96ooshjirrdq8brfckhn91sp7.apps.googleusercontent.com",
          "client_type": 1,
          "android_info": {
            "package_name": "com.example.proiectandroiddami",
            "certificate_hash": "1258d754204c245c8ff6f30980f8445be01a6109"
          }
        },
        {
          "client_id": "325462268268-vj2fgr6op2et7lepntdf22jcqtis5q77.apps.googleusercontent.com",
          "client_type": 3
        }
      ],
      "api_key": [
        {
          "current_key": "AIzaSyAuqnv4Jh1E-FC30QVMrlGIZgSo1EVWh4k"
        }
      ],
      "services": {
        "appinvite_service": {
          "other_platform_oauth_client": [
            {
              "client_id": "325462268268-vj2fgr6op2et7lepntdf22jcqtis5q77.apps.googleusercontent.com",
              "client_type": 3
            }
          ]
        }
      }
    }
  ],
  "configuration_version": "1"
}